pprinty/__init__.py
pprinty/pprint.py
tests/tests/__init__.py
tests/tests/pprint/__init__.py
tests/tests/pprint/test_pprint.py
pprinty-1.1.0.dist-info/LICENSE
pprinty-1.1.0.dist-info/METADATA
pprinty-1.1.0.dist-info/WHEEL
pprinty-1.1.0.dist-info/top_level.txt
pprinty-1.1.0.dist-info/RECORD
