Metadata-Version: 2.1
Name: pprinty
Version: 1.1.0
Summary: A package for beautiful printing of objects.
Home-page: https://github.com/Abstract-X/pprinty
Author: Abstract-X
Author-email: abstract-x-mail@protonmail.com
License: MIT
Platform: UNKNOWN
Classifier: Development Status :: 5 - Production/Stable
Classifier: Operating System :: OS Independent
Classifier: License :: OSI Approved :: MIT License
Classifier: Programming Language :: Python :: 3.7
Classifier: Programming Language :: Python :: 3.8
Classifier: Programming Language :: Python :: 3.9
Classifier: Programming Language :: Python :: 3.10
Classifier: Programming Language :: Python :: 3.11
Requires-Python: >=3.7
License-File: LICENSE
